masterbrain/__init__.py
masterbrain-0.0.1.dist-info/METADATA
masterbrain-0.0.1.dist-info/WHEEL
masterbrain-0.0.1.dist-info/licenses/LICENSE
masterbrain-0.0.1.dist-info/RECORD
