Metadata-Version: 2.4
Name: masterbrain
Version: 0.0.1
Summary: Airalogy MasterBrain
Author: Airalogy MasterBrain Team
License-Expression: Apache-2.0
License-File: LICENSE
Classifier: Programming Language :: Python :: 3.12
Requires-Python: >=3.12
